ggtrans-2.4.1.data/scripts/translate
googletrans/__init__.py
googletrans/adapters.py
googletrans/client.py
googletrans/compat.py
googletrans/constants.py
googletrans/gtoken.py
googletrans/models.py
googletrans/urls.py
googletrans/utils.py
ggtrans-2.4.1.dist-info/LICENSE
ggtrans-2.4.1.dist-info/METADATA
ggtrans-2.4.1.dist-info/WHEEL
ggtrans-2.4.1.dist-info/top_level.txt
ggtrans-2.4.1.dist-info/RECORD
