Metadata-Version: 2.1
Name: ggtrans
Version: 2.4.1
Summary: Free Google Translate API for Python. Translates totally free of charge.
Home-page: https://github.com/poipoii/py-googletrans
Author: poipoii
Author-email: earth.sama@gmail.com
License: MIT
Keywords: google translate translator
Platform: UNKNOWN
Classifier: Development Status :: 5 - Production/Stable
Classifier: Intended Audience :: Education
Classifier: Intended Audience :: End Users/Desktop
Classifier: License :: Freeware
Classifier: Operating System :: POSIX
Classifier: Operating System :: Microsoft :: Windows
Classifier: Operating System :: MacOS :: MacOS X
Classifier: Topic :: Education
Classifier: Programming Language :: Python
Classifier: Programming Language :: Python :: 2.7
Classifier: Programming Language :: Python :: 3.6
Classifier: Programming Language :: Python :: 3.7
Requires-Python: >=2.7
Requires-Dist: requests
Provides-Extra: h2
Requires-Dist: hyper ; extra == 'h2'
